cloud_function_framework/__init__.py
cloud_function_framework/cli.py
cloud_function_framework/helpers.py
cloud_function_framework/project_setup.py
cloud_function_framework-0.2.1.dist-info/METADATA
cloud_function_framework-0.2.1.dist-info/WHEEL
cloud_function_framework-0.2.1.dist-info/entry_points.txt
cloud_function_framework-0.2.1.dist-info/top_level.txt
cloud_function_framework-0.2.1.dist-info/RECORD
