Metadata-Version: 2.1
Name: cloud-function-framework
Version: 0.2.1
Summary: A CLI tool to bootstrap Google Cloud Functions projects.
Home-page: https://github.com/Lolo1883/cloud-function-framework.git
Author: Mohamed Hammad & Mohamed Abulazm
Author-email: hammad.mohamed1893@gmail.com
Classifier: Programming Language :: Python :: 3
Classifier: License :: OSI Approved :: MIT License
Classifier: Operating System :: OS Independent
Requires-Python: >=3.6
Requires-Dist: click>=8.0.0
Requires-Dist: flask>=2.0.0
